pycotap/__init__.py
pycotap/__main__.py
pycotap-1.3.0.data/data/COPYING
pycotap-1.3.0.dist-info/COPYING
pycotap-1.3.0.dist-info/METADATA
pycotap-1.3.0.dist-info/WHEEL
pycotap-1.3.0.dist-info/top_level.txt
pycotap-1.3.0.dist-info/RECORD
