Metadata-Version: 2.1
Name: pycotap
Version: 1.3.0
Summary: A tiny test runner that outputs TAP results to standard output.
Home-page: https://el-tramo.be/pycotap
Author: Remko Tronçon
Author-email: dev@el-tramo.be
License: MIT
Keywords: tap unittest testing
Classifier: Development Status :: 5 - Production/Stable
Classifier: Intended Audience :: Developers
Classifier: Topic :: Utilities
Classifier: License :: OSI Approved :: MIT License
Classifier: Topic :: Software Development :: Libraries :: Python Modules
Classifier: Topic :: Software Development :: Testing
License-File: COPYING
